df_explorer/__init__.py
df_explorer/app.py
df_explorer/debugger.py
df_explorer/werk.py
df_explorer/shared/debugger.js
df_explorer/shared/style.css
df_explorer/templates/index.html
df_explorer-0.0.3.dist-info/DESCRIPTION.rst
df_explorer-0.0.3.dist-info/METADATA
df_explorer-0.0.3.dist-info/RECORD
df_explorer-0.0.3.dist-info/WHEEL
df_explorer-0.0.3.dist-info/entry_points.txt
df_explorer-0.0.3.dist-info/metadata.json
df_explorer-0.0.3.dist-info/top_level.txt
