Metadata-Version: 1.0
Name: df-explorer
Version: 0.0.3
Summary: "Dataframe explorer"
Home-page: UNKNOWN
Author: UNKNOWN
Author-email: UNKNOWN
License: UNKNOWN
Platform: UNKNOWN
